setup.py
softsynth.egg-info/PKG-INFO
softsynth.egg-info/SOURCES.txt
softsynth.egg-info/dependency_links.txt
softsynth.egg-info/entry_points.txt
softsynth.egg-info/requires.txt
softsynth.egg-info/top_level.txt
synth/__init__.py
synth/channel.py
synth/envelopes.py
synth/filters.py
synth/interfaces.py
synth/main.py
synth/new_filters.py
synth/note_envelopes.py
synth/options.py
synth/oscillator.py
synth/pcm.py
synth/stream.py
synth/synthesizer.py
synth/wave_writer.py
synth/instruments/BaseInstrument.py
synth/instruments/OvertoneInstrument.py
synth/instruments/PercussionInstrument.py
synth/instruments/SynthInstrument.py
synth/instruments/__init__.py
synth/midi/MidiEvent.py
synth/midi/MidiFileParser.py
synth/midi/MidiHeader.py
synth/midi/MidiTrack.py
synth/midi/__init__.py
synth/midi/utils.py