Metadata-Version: 1.1
Name: softsynth
Version: 0.3.2
Summary: Proof of concept software synthesizer
Home-page: https://github.com/bspaans/python-softsynth
Author: Bart Spaans
Author-email: bart.spaans@gmail.com
License: GPLv3
Platform: UNKNOWN
Classifier: Intended Audience :: Developers
Classifier: Intended Audience :: Other Audience
Classifier: License :: OSI Approved :: GNU General Public License (GPL)
Classifier: Operating System :: OS Independent
Classifier: Programming Language :: Python
Classifier: Topic :: Artistic Software
Classifier: Topic :: Education
Classifier: Topic :: Multimedia
Classifier: Topic :: Multimedia :: Sound/Audio
Classifier: Topic :: Multimedia :: Sound/Audio :: MIDI
